neurapython/__init__.py
neurapython-2.0.4.dist-info/METADATA
neurapython-2.0.4.dist-info/WHEEL
neurapython-2.0.4.dist-info/top_level.txt
neurapython-2.0.4.dist-info/RECORD
