Metadata-Version: 2.4
Name: NeuraPython
Version: 2.0.4
Summary: NeuraPython is a unified framework combining AI, Machine Learning, Data Science, Web Development, Scientific Computation, and Utility tools.
Home-page: https://github.com/IbrahimShahid7767/neurapython
Author: Ibrahim Shahid
Author-email: ibrahimshahid7767@gmail.com
License: MIT
Project-URL: Bug Tracker, https://github.com/IbrahimShahid7767/neurapython/issues
Project-URL: Documentation, https://pypi.org/project/NeuraPython/
Keywords: AI,Machine Learning,Deep Learning,Data Science,Physics,Chemistry,Math,Flask,Neural Network,Utility,Automation,Computation
Classifier: Programming Language :: Python :: 3
Classifier: License :: OSI Approved :: MIT License
Classifier: Operating System :: OS Independent
Classifier: Intended Audience :: Developers
Classifier: Topic :: Scientific/Engineering :: Artificial Intelligence
Classifier: Topic :: Software Development :: Libraries
Requires-Python: >=3.8
Requires-Dist: numpy
Requires-Dist: pandas
Requires-Dist: matplotlib
Requires-Dist: pygame
Requires-Dist: opencv-python
Requires-Dist: pyttsx3
Requires-Dist: speechrecognition
Requires-Dist: flask
Requires-Dist: scikit-learn
Requires-Dist: pdfplumber
Requires-Dist: pdf2docx
Requires-Dist: docx2pdf
Requires-Dist: fpdf
Requires-Dist: markdown
Requires-Dist: beautifulsoup4
Requires-Dist: sympy
Requires-Dist: tensorflow
Requires-Dist: torch
Requires-Dist: joblib
Requires-Dist: qrcode
Requires-Dist: requests
Requires-Dist: pillow
Dynamic: author
Dynamic: author-email
Dynamic: classifier
Dynamic: description
Dynamic: description-content-type
Dynamic: home-page
Dynamic: keywords
Dynamic: license
Dynamic: project-url
Dynamic: requires-dist
Dynamic: requires-python
Dynamic: summary
